ospac/__init__.py
ospac/cli/__init__.py
ospac/cli/commands.py
ospac/core/compatibility_matrix.py
ospac/data/licenses/json/0BSD.json
ospac/data/licenses/json/3D-Slicer-1.0.json
ospac/data/licenses/json/AAL.json
ospac/data/licenses/json/ADSL.json
ospac/data/licenses/json/AFL-1.1.json
ospac/data/licenses/json/AFL-1.2.json
ospac/data/licenses/json/AFL-2.0.json
ospac/data/licenses/json/AFL-2.1.json
ospac/data/licenses/json/AFL-3.0.json
ospac/data/licenses/json/AGPL-1.0-only.json
ospac/data/licenses/json/AGPL-1.0-or-later.json
ospac/data/licenses/json/AGPL-1.0.json
ospac/data/licenses/json/AGPL-3.0-only.json
ospac/data/licenses/json/AGPL-3.0-or-later.json
ospac/data/licenses/json/AGPL-3.0.json
ospac/data/licenses/json/AMD-newlib.json
ospac/data/licenses/json/AMDPLPA.json
ospac/data/licenses/json/AML-glslang.json
ospac/data/licenses/json/AML.json
ospac/data/licenses/json/AMPAS.json
ospac/data/licenses/json/ANTLR-PD-fallback.json
ospac/data/licenses/json/ANTLR-PD.json
ospac/data/licenses/json/APAFML.json
ospac/data/licenses/json/APL-1.0.json
ospac/data/licenses/json/APSL-1.0.json
ospac/data/licenses/json/APSL-1.1.json
ospac/data/licenses/json/APSL-1.2.json
ospac/data/licenses/json/APSL-2.0.json
ospac/data/licenses/json/ASWF-Digital-Assets-1.0.json
ospac/data/licenses/json/ASWF-Digital-Assets-1.1.json
ospac/data/licenses/json/Abstyles.json
ospac/data/licenses/json/AdaCore-doc.json
ospac/data/licenses/json/Adobe-2006.json
ospac/data/licenses/json/Adobe-Display-PostScript.json
ospac/data/licenses/json/Adobe-Glyph.json
ospac/data/licenses/json/Adobe-Utopia.json
ospac/data/licenses/json/Advanced-Cryptics-Dictionary.json
ospac/data/licenses/json/Afmparse.json
ospac/data/licenses/json/Aladdin.json
ospac/data/licenses/json/Apache-1.0.json
ospac/data/licenses/json/Apache-1.1.json
ospac/data/licenses/json/Apache-2.0.json
ospac/data/licenses/json/App-s2p.json
ospac/data/licenses/json/Arphic-1999.json
ospac/data/licenses/json/Artistic-1.0-Perl.json
ospac-1.2.5.dist-info/licenses/AUTHORS.md
ospac-1.2.5.dist-info/licenses/LICENSE
ospac-1.2.5.dist-info/METADATA
ospac-1.2.5.dist-info/WHEEL
ospac-1.2.5.dist-info/entry_points.txt
ospac-1.2.5.dist-info/top_level.txt
ospac-1.2.5.dist-info/RECORD
