Metadata-Version: 2.4
Name: ospac
Version: 1.2.5
Summary: Open Source Policy as Code - License compliance policy engine
Author-email: "Oscar Valenzuela B." <oscar.valenzuela.b@gmail.com>
Maintainer-email: "Oscar Valenzuela B." <oscar.valenzuela.b@gmail.com>
License-Expression: Apache-2.0
Project-URL: Homepage, https://github.com/SemClone/ospac
Project-URL: Documentation, https://github.com/SemClone/ospac#readme
Project-URL: Repository, https://github.com/SemClone/ospac.git
Project-URL: Issues, https://github.com/SemClone/ospac/issues
Project-URL: Changelog, https://github.com/SemClone/ospac/blob/main/CHANGELOG.md
Keywords: license,compliance,policy,policy-as-code,oss,open-source,spdx,license-compatibility,regulatory-compliance,sbom
Classifier: Development Status :: 4 - Beta
Classifier: Intended Audience :: Developers
Classifier: Intended Audience :: Legal Industry
Classifier: Topic :: Software Development :: Libraries :: Python Modules
Classifier: Topic :: Software Development :: Documentation
Classifier: Topic :: System :: Software Distribution
Classifier: Programming Language :: Python :: 3
Classifier: Programming Language :: Python :: 3.10
Classifier: Programming Language :: Python :: 3.11
Classifier: Programming Language :: Python :: 3.12
Classifier: Operating System :: OS Independent
Requires-Python: >=3.10
License-File: LICENSE
License-File: AUTHORS.md
Requires-Dist: pyyaml>=6.0
Requires-Dist: click>=8.0.0
Requires-Dist: jsonschema>=4.17.0
Requires-Dist: jinja2>=3.0.0
Requires-Dist: colorama>=0.4.0
Requires-Dist: requests>=2.28.0
Requires-Dist: urllib3<2.0,>=1.26.0; python_version < "3.10"
Requires-Dist: urllib3>=1.26.0; python_version >= "3.10"
Provides-Extra: dev
Requires-Dist: pytest>=7.0.0; extra == "dev"
Requires-Dist: pytest-cov>=4.0.0; extra == "dev"
Requires-Dist: pytest-asyncio>=0.21.0; extra == "dev"
Requires-Dist: black>=23.0.0; extra == "dev"
Requires-Dist: flake8>=6.0.0; extra == "dev"
Requires-Dist: mypy>=1.0.0; extra == "dev"
Requires-Dist: isort>=5.12.0; extra == "dev"
Requires-Dist: pre-commit>=3.0.0; extra == "dev"
Provides-Extra: test
Requires-Dist: pytest>=7.0.0; extra == "test"
Requires-Dist: pytest-cov>=4.0.0; extra == "test"
Requires-Dist: pytest-asyncio>=0.21.0; extra == "test"
Provides-Extra: semcl
Requires-Dist: osslili>=1.5.0; extra == "semcl"
Requires-Dist: upmex>=1.6.0; extra == "semcl"
Provides-Extra: llm
Requires-Dist: strands-agents>=0.1.0; extra == "llm"
Provides-Extra: all
Requires-Dist: ospac[llm,semcl]; extra == "all"
Dynamic: license-file
